MANIFEST.in
README.md
setup.cfg
setup.py
tests/__init__.py
tests/test_unithon.py
unithon/__init__.py
unithon/load_samples.py
unithon.egg-info/PKG-INFO
unithon.egg-info/SOURCES.txt
unithon.egg-info/dependency_links.txt
unithon.egg-info/requires.txt
unithon.egg-info/top_level.txt
unithon/data/__init__.py
unithon/data/test.csv