Metadata-Version: 2.1
Name: unithon
Version: 0.0.2
Summary: unithon - Python library to unify datasets
Home-page: https://github.com/dvidgar/unithon
Author: David Garcia
Author-email: dvid@usal.es
License: Apache License 2.0
Download-URL: https://github.com/dvidgar/unithon/archive/0.0.2.tar.gz
Keywords: unithon,datasets,unification,data-science
Platform: UNKNOWN
Classifier: Development Status :: 2 - Pre-Alpha
Classifier: Programming Language :: Python :: 3.7
Classifier: License :: OSI Approved :: Apache Software License
Classifier: Intended Audience :: Developers
Classifier: Topic :: Scientific/Engineering
Classifier: Topic :: Scientific/Engineering :: Artificial Intelligence
Classifier: Topic :: Scientific/Engineering :: Information Analysis
Classifier: Topic :: Software Development :: Libraries
